smeterd/__init__.py
smeterd/__main__.py
smeterd/meter.py
smeterd/cli/__init__.py
smeterd/cli/read_meter.py
smeterd-2.9.2.dist-info/LICENSE
smeterd-2.9.2.dist-info/METADATA
smeterd-2.9.2.dist-info/WHEEL
smeterd-2.9.2.dist-info/entry_points.txt
smeterd-2.9.2.dist-info/top_level.txt
smeterd-2.9.2.dist-info/RECORD
