Metadata-Version: 2.1
Name: smeterd
Version: 2.9.2
Summary: Read smart meter P1 packets
Home-page: https://github.com/nrocco/smeterd
Author: Nico Di Rocco
Author-email: dirocco.nico@gmail.com
License: GPLv3
Keywords: smartmeter,kwh,gas,p1
Platform: any
Classifier: Development Status :: 5 - Production/Stable
Classifier: Environment :: Console
Classifier: License :: OSI Approved :: GNU General Public License v3 (GPLv3)
Classifier: Operating System :: Unix
Classifier: Programming Language :: Python
Classifier: Programming Language :: Python :: 3
Classifier: Programming Language :: Python :: 3.7
Classifier: Programming Language :: Python :: 3.8
Classifier: Programming Language :: Python :: 3.9
Classifier: Programming Language :: Python :: 3.10
Classifier: Topic :: Software Development :: Libraries :: Python Modules
Classifier: Topic :: Utilities
Requires-Python: >=3.7
License-File: LICENSE
Requires-Dist: click
Requires-Dist: crcmod
Requires-Dist: pyserial
Provides-Extra: develop
Requires-Dist: pytest ; extra == 'develop'
Requires-Dist: pytest-cov ; extra == 'develop'
